{
  "belief-control": {
    "metrics": {
      "lessons_count": 9,
      "lessons_avg_length": 17.0,
      "beliefs_count": 6,
      "observed_count": 6,
      "theorized_count": 0,
      "frontier_open": 8,
      "frontier_resolved": 3,
      "principles_count": 2,
      "total_files": 28,
      "total_lines": 557,
      "has_tools": true,
      "has_workspace": true,
      "validator_passes": true,
      "commit_count": 5
    },
    "fitness": 171.0,
    "evaluated": "2026-02-26"
  },
  "belief-no-falsification": {
    "metrics": {
      "lessons_count": 12,
      "lessons_avg_length": 17.0,
      "beliefs_count": 11,
      "observed_count": 8,
      "theorized_count": 3,
      "frontier_open": 9,
      "frontier_resolved": 4,
      "principles_count": 19,
      "total_files": 31,
      "total_lines": 671,
      "has_tools": true,
      "has_workspace": true,
      "validator_passes": true,
      "commit_count": 7
    },
    "fitness": 264.0,
    "evaluated": "2026-02-26"
  },
  "belief-minimal": {
    "metrics": {
      "lessons_count": 12,
      "lessons_avg_length": 17.75,
      "beliefs_count": 10,
      "observed_count": 10,
      "theorized_count": 0,
      "frontier_open": 4,
      "frontier_resolved": 4,
      "principles_count": 0,
      "total_files": 34,
      "total_lines": 1214,
      "has_tools": true,
      "has_workspace": true,
      "validator_passes": true,
      "commit_count": 6
    },
    "fitness": 236.0,
    "evaluated": "2026-02-26"
  },
  "belief-no-modes": {
    "metrics": {
      "lessons_count": 6,
      "lessons_avg_length": 17.0,
      "beliefs_count": 4,
      "observed_count": 4,
      "theorized_count": 0,
      "frontier_open": 4,
      "frontier_resolved": 4,
      "principles_count": 2,
      "total_files": 25,
      "total_lines": 447,
      "has_tools": true,
      "has_workspace": true,
      "validator_passes": true,
      "commit_count": 4
    },
    "fitness": 132.0,
    "evaluated": "2026-02-26"
  },
  "belief-no-lesson-limit": {
    "metrics": {
      "lessons_count": 7,
      "lessons_avg_length": 55.42857142857143,
      "beliefs_count": 8,
      "observed_count": 8,
      "theorized_count": 0,
      "frontier_open": 9,
      "frontier_resolved": 3,
      "principles_count": 11,
      "total_files": 26,
      "total_lines": 836,
      "has_tools": true,
      "has_workspace": true,
      "validator_passes": true,
      "commit_count": 4
    },
    "fitness": 204.0,
    "evaluated": "2026-02-26"
  },
  "belief-aggressive-challenge": {
    "metrics": {
      "lessons_count": 7,
      "lessons_avg_length": 15.428571428571429,
      "beliefs_count": 6,
      "observed_count": 3,
      "theorized_count": 3,
      "frontier_open": 8,
      "frontier_resolved": 3,
      "principles_count": 2,
      "total_files": 26,
      "total_lines": 512,
      "has_tools": true,
      "has_workspace": true,
      "validator_passes": true,
      "commit_count": 5
    },
    "fitness": 135.0,
    "evaluated": "2026-02-26"
  },
  "belief-nofalsif-aggressive": {
    "metrics": {
      "lessons_count": 7,
      "lessons_avg_length": 16.857142857142858,
      "beliefs_count": 8,
      "observed_count": 7,
      "theorized_count": 1,
      "frontier_open": 5,
      "frontier_resolved": 7,
      "principles_count": 2,
      "total_files": 26,
      "total_lines": 537,
      "has_tools": true,
      "has_workspace": true,
      "validator_passes": true,
      "commit_count": 4
    },
    "fitness": 198.0,
    "evaluated": "2026-02-26"
  },
  "belief-nofalsif-nolimit": {
    "metrics": {
      "lessons_count": 10,
      "lessons_avg_length": 34.8,
      "beliefs_count": 8,
      "observed_count": 8,
      "theorized_count": 0,
      "frontier_open": 10,
      "frontier_resolved": 3,
      "principles_count": 2,
      "total_files": 29,
      "total_lines": 765,
      "has_tools": true,
      "has_workspace": true,
      "validator_passes": true,
      "commit_count": 6
    },
    "fitness": 196.0,
    "evaluated": "2026-02-26"
  },
  "belief-nolimit-aggressive": {
    "metrics": {
      "lessons_count": 6,
      "lessons_avg_length": 49.166666666666664,
      "beliefs_count": 6,
      "observed_count": 5,
      "theorized_count": 1,
      "frontier_open": 8,
      "frontier_resolved": 5,
      "principles_count": 2,
      "total_files": 25,
      "total_lines": 717,
      "has_tools": true,
      "has_workspace": true,
      "validator_passes": true,
      "commit_count": 4
    },
    "fitness": 150.0,
    "evaluated": "2026-02-26"
  },
  "belief-minimal-nofalsif": {
    "metrics": {
      "lessons_count": 7,
      "lessons_avg_length": 16.857142857142858,
      "beliefs_count": 10,
      "observed_count": 8,
      "theorized_count": 2,
      "frontier_open": 9,
      "frontier_resolved": 2,
      "principles_count": 0,
      "total_files": 22,
      "total_lines": 446,
      "has_tools": true,
      "has_workspace": true,
      "validator_passes": true,
      "commit_count": 2
    },
    "fitness": 198.0,
    "evaluated": "2026-02-26"
  },
  "belief-aggressive-minimal": {
    "metrics": {
      "lessons_count": 3,
      "lessons_avg_length": 15.333333333333334,
      "beliefs_count": 7,
      "observed_count": 6,
      "theorized_count": 1,
      "frontier_open": 8,
      "frontier_resolved": 2,
      "principles_count": 0,
      "total_files": 18,
      "total_lines": 384,
      "has_tools": true,
      "has_workspace": true,
      "validator_passes": true,
      "commit_count": 2
    },
    "fitness": 150.0,
    "evaluated": "2026-02-26"
  },
  "belief-principles-first": {
    "metrics": {
      "lessons_count": 3,
      "lessons_avg_length": 13.666666666666666,
      "beliefs_count": 7,
      "observed_count": 6,
      "theorized_count": 1,
      "frontier_open": 7,
      "frontier_resolved": 2,
      "principles_count": 7,
      "total_files": 22,
      "total_lines": 425,
      "has_tools": true,
      "has_workspace": true,
      "validator_passes": true,
      "commit_count": 2
    },
    "fitness": 163.0,
    "evaluated": "2026-02-26"
  },
  "belief-test-first": {
    "metrics": {
      "lessons_count": 5,
      "lessons_avg_length": 16.2,
      "beliefs_count": 8,
      "observed_count": 8,
      "theorized_count": 0,
      "frontier_open": 9,
      "frontier_resolved": 2,
      "principles_count": 2,
      "total_files": 24,
      "total_lines": 482,
      "has_tools": true,
      "has_workspace": true,
      "validator_passes": true,
      "commit_count": 1
    },
    "fitness": 186.0,
    "evaluated": "2026-02-26"
  }
}