{
  "total_lessons": 657,
  "high_citation_lessons": 68,
  "threshold": 5,
  "patterns": {
    "n1_inflation": {
      "count": 28,
      "flags": [
        {
          "lesson": "L-253",
          "in_degree": 5,
          "confidence": "Measured",
          "pattern": "n=1 inflation (possible)",
          "reason": "measured without explicit sample size \u226510",
          "title": "L-253: F-FIN1 CONFIRMED for quality metric \u2014 portfolio variance reduction holds (0.6% off 1/\u221a3)"
        },
        {
          "lesson": "L-421",
          "in_degree": 5,
          "confidence": "Measured",
          "pattern": "n=1 inflation (possible)",
          "reason": "measured without explicit sample size \u226510",
          "title": "L-421 \u2014 NK lesson graph crossed K_avg=1.0 threshold (S305\u2192S312)"
        },
        {
          "lesson": "L-448",
          "in_degree": 6,
          "confidence": "Measured",
          "pattern": "n=1 inflation (possible)",
          "reason": "measured without explicit sample size \u226510",
          "title": "L-448: NK Citation Graph Plateau \u2014 ISO Sprints Don't Move K_avg"
        },
        {
          "lesson": "L-462",
          "in_degree": 5,
          "confidence": "Measured",
          "pattern": "n=1 inflation (possible)",
          "reason": "measured without explicit sample size \u226510",
          "title": "L-462: NK quality gate prevents orphan dilution \u2014 K_avg self-sustaining above 1.5"
        },
        {
          "lesson": "L-490",
          "in_degree": 7,
          "confidence": "Theorized",
          "pattern": "n=1 inflation",
          "reason": "weak confidence",
          "title": "L-490: Human authority de-privileging follows a 4-phase arc \u2014 each phase human-initiated"
        },
        {
          "lesson": "L-492",
          "in_degree": 8,
          "confidence": "Measured",
          "pattern": "n=1 inflation (possible)",
          "reason": "measured without explicit sample size \u226510",
          "title": "L-492: Citation density acceleration \u2014 quality gates create self-reinforcing citation growth"
        },
        {
          "lesson": "L-497",
          "in_degree": 6,
          "confidence": "Measured (n=4 domains, 5 convergent findings) | Sharpe: 5",
          "pattern": "n=1 inflation (possible)",
          "reason": "measured without explicit sample size \u226510",
          "title": "L-497: DNA replication/mutation council \u2014 swarm has Darwinian components but disconnected"
        },
        {
          "lesson": "L-501",
          "in_degree": 5,
          "confidence": "Measured (5-domain council, 11 source lessons, 39-session colony gap) | Sharpe: 5",
          "pattern": "n=1 inflation (possible)",
          "reason": "measured without explicit sample size \u226510",
          "title": "L-501: Expert dispatch is PHIL-2's test case \u2014 the function that forgot to apply to itself"
        },
        {
          "lesson": "L-506",
          "in_degree": 6,
          "confidence": "Measured (n=1 implementation, outcome_map parsing 40+ lanes) | Sharpe: 4",
          "pattern": "n=1 inflation",
          "reason": "n=1",
          "title": "L-506: Outcome feedback closes PHIL-2 \u2014 dispatch learning from its own dispatch outcomes"
        },
        {
          "lesson": "L-520",
          "in_degree": 8,
          "confidence": "Measured",
          "pattern": "n=1 inflation (possible)",
          "reason": "measured without explicit sample size \u226510",
          "title": "L-520: Experiment\u2192lesson bottleneck is 89% loss \u2014 volume-conversion paradox across domains"
        },
        {
          "lesson": "L-526",
          "in_degree": 13,
          "confidence": "Measured",
          "pattern": "n=1 inflation (possible)",
          "reason": "measured without explicit sample size \u226510",
          "title": "L-526: Planning obsolescence window \u2014 orient\u2192execute gap exceeds concurrent commit rate"
        },
        {
          "lesson": "L-533",
          "in_degree": 5,
          "confidence": "Theorized",
          "pattern": "n=1 inflation",
          "reason": "weak confidence",
          "title": "L-533: 21 tools self-swarm but only 6 close the action loop \u2014 GAP-1 is the binding constraint"
        },
        {
          "lesson": "L-537",
          "in_degree": 5,
          "confidence": "Theorized",
          "pattern": "n=1 inflation",
          "reason": "weak confidence",
          "title": "L-537: Bounded-epistemic self-replication \u2014 local ignorance IS the mechanism (ISO-20)"
        },
        {
          "lesson": "L-556",
          "in_degree": 8,
          "confidence": "Measured",
          "pattern": "n=1 inflation (possible)",
          "reason": "measured without explicit sample size \u226510",
          "title": "<!-- SUPERSEDED BY L-555: near-duplicate (sim=0.92), same finding, same session S357 -->"
        },
        {
          "lesson": "L-557",
          "in_degree": 8,
          "confidence": "Measured",
          "pattern": "n=1 inflation (possible)",
          "reason": "measured without explicit sample size \u226510",
          "title": "L-557: C-EDIT conflict \u2014 DUE-item convergence costs 37% overhead, soft-claim prevents 67%"
        },
        {
          "lesson": "L-571",
          "in_degree": 8,
          "confidence": "Measured",
          "pattern": "n=1 inflation (possible)",
          "reason": "measured without explicit sample size \u226510",
          "title": "L-571: Dispatch scores concentrate work, not spread it \u2014 exploitation amplifier, not diversity mechanism"
        },
        {
          "lesson": "L-574",
          "in_degree": 9,
          "confidence": "Measured",
          "pattern": "n=1 inflation (possible)",
          "reason": "measured without explicit sample size \u226510",
          "title": "L-574: Dark matter inflated 2.5x by measurement gap \u2014 Domain: field invisible to dream.py"
        },
        {
          "lesson": "L-577",
          "in_degree": 11,
          "confidence": "Measured",
          "pattern": "n=1 inflation (possible)",
          "reason": "measured without explicit sample size \u226510",
          "title": "L-577: Session yield is highly skewed (mode=0, max=14) \u2014 non-ergodicity is a feature, not a flaw"
        },
        {
          "lesson": "L-599",
          "in_degree": 14,
          "confidence": "Measured",
          "pattern": "n=1 inflation (possible)",
          "reason": "measured without explicit sample size \u226510",
          "title": "L-599: Hallucination audit \u2014 metaphor-to-measurement pipeline is the root failure mode"
        },
        {
          "lesson": "L-621",
          "in_degree": 6,
          "confidence": "Measured",
          "pattern": "n=1 inflation (possible)",
          "reason": "measured without explicit sample size \u226510",
          "title": "L-621: Visit saturation + exploration mode reduces dispatch score concentration 37% \u2014 exploitation amplification treatable"
        },
        {
          "lesson": "L-625",
          "in_degree": 5,
          "confidence": "Theorized",
          "pattern": "n=1 inflation",
          "reason": "weak confidence",
          "title": "L-625: Heat tracker archive blindness \u2014 30+ domains misclassified as NEW despite 47 visits"
        },
        {
          "lesson": "L-629",
          "in_degree": 9,
          "confidence": "Measured",
          "pattern": "n=1 inflation (possible)",
          "reason": "measured without explicit sample size \u226510",
          "title": "L-629: Concurrency-throughput is constant, not USL \u2014 total lesson production independent of N"
        },
        {
          "lesson": "L-633",
          "in_degree": 6,
          "confidence": "Measured",
          "pattern": "n=1 inflation (possible)",
          "reason": "measured without explicit sample size \u226510",
          "title": "L-633: Knowledge decays at the mechanism layer, not the principle layer \u2014 5% framing-contradicted, 20% mechanism-superseded"
        },
        {
          "lesson": "L-636",
          "in_degree": 5,
          "confidence": "Measured",
          "pattern": "n=1 inflation (possible)",
          "reason": "measured without explicit sample size \u226510",
          "title": "L-636: B1 PARTIALLY FALSIFIED at N=572 \u2014 storage holds, INDEX.md retrieval past 20% threshold"
        },
        {
          "lesson": "L-644",
          "in_degree": 6,
          "confidence": "Measured",
          "pattern": "n=1 inflation (possible)",
          "reason": "measured without explicit sample size \u226510",
          "title": "L-644: 44.8% tool abandonment \u2014 frontier experiment tools are single-session artifacts"
        },
        {
          "lesson": "L-646",
          "in_degree": 8,
          "confidence": "Measured",
          "pattern": "n=1 inflation (possible)",
          "reason": "measured without explicit sample size \u226510",
          "title": "L-646: Predictive coding operational \u2014 loop closure drives quality, not prediction alone"
        },
        {
          "lesson": "L-707",
          "in_degree": 5,
          "confidence": "Measured",
          "pattern": "n=1 inflation (possible)",
          "reason": "measured without explicit sample size \u226510",
          "title": "L-707 Epistemological State Model \u2014 swarm stores content but lacks knowledge-state reasoning"
        },
        {
          "lesson": "L-710",
          "in_degree": 5,
          "confidence": "measured (n=5 layers, n=5 attack vectors) | Sharpe: 8",
          "pattern": "n=1 inflation (possible)",
          "reason": "measured without explicit sample size \u226510",
          "title": "L-710: Genesis security protocol 0/5 mitigated after 68 sessions \u2014 L-601 decay confirmed"
        }
      ]
    },
    "citation_loops": {
      "count": 28,
      "flags": [
        {
          "lessons": [
            "L-39",
            "L-42"
          ],
          "combined_in_degree": 40,
          "pattern": "citation loop",
          "titles": [
            "L-039: NK analysis at scale \u2014 K/N fails, K_avg*N+Cycles works",
            "L-042: Automated NK analysis validates composite metric at scale"
          ]
        },
        {
          "lessons": [
            "L-25",
            "L-39"
          ],
          "combined_in_degree": 35,
          "pattern": "citation loop",
          "titles": [
            "L-025: Tune belief interconnection K toward edge of chaos (Kauffman NK model)",
            "L-039: NK analysis at scale \u2014 K/N fails, K_avg*N+Cycles works"
          ]
        },
        {
          "lessons": [
            "L-39",
            "L-44"
          ],
          "combined_in_degree": 35,
          "pattern": "citation loop",
          "titles": [
            "L-039: NK analysis at scale \u2014 K/N fails, K_avg*N+Cycles works",
            "L-044: Cycle count independently predicts bug accumulation better than K_avg or composite"
          ]
        },
        {
          "lessons": [
            "L-39",
            "L-55"
          ],
          "combined_in_degree": 31,
          "pattern": "citation loop",
          "titles": [
            "L-039: NK analysis at scale \u2014 K/N fails, K_avg*N+Cycles works",
            "L-055: Cycles predict maintenance burden better than composite (rho=0.917)"
          ]
        },
        {
          "lessons": [
            "L-35",
            "L-39"
          ],
          "combined_in_degree": 29,
          "pattern": "citation loop",
          "titles": [
            "L-035: Complexity theory tools work on external systems (tool coupling analysis)",
            "L-039: NK analysis at scale \u2014 K/N fails, K_avg*N+Cycles works"
          ]
        },
        {
          "lessons": [
            "L-42",
            "L-44"
          ],
          "combined_in_degree": 29,
          "pattern": "citation loop",
          "titles": [
            "L-042: Automated NK analysis validates composite metric at scale",
            "L-044: Cycle count independently predicts bug accumulation better than K_avg or composite"
          ]
        },
        {
          "lessons": [
            "L-1",
            "L-15"
          ],
          "combined_in_degree": 25,
          "pattern": "citation loop",
          "titles": [
            "L-001: Genesis validation \u2014 the setup mostly works",
            "L-015: The frontier IS the self-assignment mechanism"
          ]
        },
        {
          "lessons": [
            "L-42",
            "L-55"
          ],
          "combined_in_degree": 25,
          "pattern": "citation loop",
          "titles": [
            "L-042: Automated NK analysis validates composite metric at scale",
            "L-055: Cycles predict maintenance burden better than composite (rho=0.917)"
          ]
        },
        {
          "lessons": [
            "L-44",
            "L-55"
          ],
          "combined_in_degree": 20,
          "pattern": "citation loop",
          "titles": [
            "L-044: Cycle count independently predicts bug accumulation better than K_avg or composite",
            "L-055: Cycles predict maintenance burden better than composite (rho=0.917)"
          ]
        },
        {
          "lessons": [
            "L-25",
            "L-26"
          ],
          "combined_in_degree": 17,
          "pattern": "citation loop",
          "titles": [
            "L-025: Tune belief interconnection K toward edge of chaos (Kauffman NK model)",
            "L-026: Measure actual coupling, not intended coupling (Simon near-decomposability)"
          ]
        },
        {
          "lessons": [
            "L-15",
            "L-19"
          ],
          "combined_in_degree": 16,
          "pattern": "citation loop",
          "titles": [
            "L-015: The frontier IS the self-assignment mechanism",
            "L-019: Context handoff \u2014 commit state, write handoff note, trust the structure"
          ]
        },
        {
          "lessons": [
            "L-44",
            "L-97"
          ],
          "combined_in_degree": 16,
          "pattern": "citation loop",
          "titles": [
            "L-044: Cycle count independently predicts bug accumulation better than K_avg or composite",
            "L-097: NK-error-handling correlation is cycle-dependent, not coupling-dependent"
          ]
        },
        {
          "lessons": [
            "L-552",
            "L-553"
          ],
          "combined_in_degree": 15,
          "pattern": "citation loop",
          "titles": [
            "L-552: Regime boundary map \u2014 9 quantified thresholds, 1 anomalous crossing, NK chaos nearest",
            "L-553: Lamarckian correction prevents quality degradation \u2014 directed revision inverts the threshold"
          ]
        },
        {
          "lessons": [
            "L-492",
            "L-510"
          ],
          "combined_in_degree": 14,
          "pattern": "citation loop",
          "titles": [
            "L-492: Citation density acceleration \u2014 quality gates create self-reinforcing citation growth",
            "L-510: K_avg inflated 11.8% by regex bug \u2014 ad-hoc AND permanent tools can drift"
          ]
        },
        {
          "lessons": [
            "L-25",
            "L-29"
          ],
          "combined_in_degree": 13,
          "pattern": "citation loop",
          "titles": [
            "L-025: Tune belief interconnection K toward edge of chaos (Kauffman NK model)",
            "L-029: Wolfram classes + Langton's \u03bb quantify edge of chaos (Shock 3)"
          ]
        },
        {
          "lessons": [
            "L-18",
            "L-19"
          ],
          "combined_in_degree": 12,
          "pattern": "citation loop",
          "titles": [
            "L-018: Concurrent sessions \u2014 git pull before commit, branch for risky work",
            "L-019: Context handoff \u2014 commit state, write handoff note, trust the structure"
          ]
        },
        {
          "lessons": [
            "L-55",
            "L-97"
          ],
          "combined_in_degree": 12,
          "pattern": "citation loop",
          "titles": [
            "L-055: Cycles predict maintenance burden better than composite (rho=0.917)",
            "L-097: NK-error-handling correlation is cycle-dependent, not coupling-dependent"
          ]
        },
        {
          "lessons": [
            "L-26",
            "L-35"
          ],
          "combined_in_degree": 11,
          "pattern": "citation loop",
          "titles": [
            "L-026: Measure actual coupling, not intended coupling (Simon near-decomposability)",
            "L-035: Complexity theory tools work on external systems (tool coupling analysis)"
          ]
        },
        {
          "lessons": [
            "L-5",
            "L-14"
          ],
          "combined_in_degree": 10,
          "pattern": "citation loop",
          "titles": [
            "L-005: This system is a blackboard+stigmergy hybrid, not a swarm",
            "L-014: External learning works \u2014 Crowston's 3 affordances for stigmergy"
          ]
        },
        {
          "lessons": [
            "L-15",
            "L-21"
          ],
          "combined_in_degree": 9,
          "pattern": "citation loop",
          "titles": [
            "L-015: The frontier IS the self-assignment mechanism",
            "L-021: Diminishing returns signal \u2014 when lessons repeat themes or go meta-meta"
          ]
        }
      ]
    },
    "cascade_amplification": {
      "count": 64,
      "flags": [
        {
          "lesson": "L-251",
          "direct_citers": 5,
          "transitive_citers": 288,
          "pattern": "cascade amplification risk",
          "title": "L-251: F-FIN1 PARTIAL \u2014 portfolio variance applies to mean-of-N, not max-of-N (wall time)",
          "confidence": ""
        },
        {
          "lesson": "L-253",
          "direct_citers": 5,
          "transitive_citers": 288,
          "pattern": "cascade amplification risk",
          "title": "L-253: F-FIN1 CONFIRMED for quality metric \u2014 portfolio variance reduction holds (0.6% off 1/\u221a3)",
          "confidence": "Measured"
        },
        {
          "lesson": "L-218",
          "direct_citers": 6,
          "transitive_citers": 286,
          "pattern": "cascade amplification risk",
          "title": "L-218: Asynchrony is a structural cascade defense \u2014 timing of decisions determines cascade direction",
          "confidence": ""
        },
        {
          "lesson": "L-297",
          "direct_citers": 5,
          "transitive_citers": 282,
          "pattern": "cascade amplification risk",
          "title": "L-297: F-CON1 baseline \u2014 C3 rate 0.4%, C1 rate 1.3%; administrative closures dominate ABANDONED",
          "confidence": ""
        },
        {
          "lesson": "L-304",
          "direct_citers": 9,
          "transitive_citers": 281,
          "pattern": "cascade amplification risk",
          "title": "L-304: SWARM-LANES state proliferation \u2014 2x bloat from 444 rows for 225 unique lanes",
          "confidence": ""
        },
        {
          "lesson": "L-5",
          "direct_citers": 9,
          "transitive_citers": 276,
          "pattern": "cascade amplification risk",
          "title": "L-005: This system is a blackboard+stigmergy hybrid, not a swarm",
          "confidence": ""
        },
        {
          "lesson": "L-283",
          "direct_citers": 7,
          "transitive_citers": 273,
          "pattern": "cascade amplification risk",
          "title": "L-283: Proof-of-novelty gate prevents wasted work in high-concurrency swarms",
          "confidence": ""
        },
        {
          "lesson": "L-1",
          "direct_citers": 18,
          "transitive_citers": 270,
          "pattern": "cascade amplification risk",
          "title": "L-001: Genesis validation \u2014 the setup mostly works",
          "confidence": ""
        },
        {
          "lesson": "L-15",
          "direct_citers": 7,
          "transitive_citers": 270,
          "pattern": "cascade amplification risk",
          "title": "L-015: The frontier IS the self-assignment mechanism",
          "confidence": ""
        },
        {
          "lesson": "L-19",
          "direct_citers": 9,
          "transitive_citers": 270,
          "pattern": "cascade amplification risk",
          "title": "L-019: Context handoff \u2014 commit state, write handoff note, trust the structure",
          "confidence": ""
        },
        {
          "lesson": "L-25",
          "direct_citers": 12,
          "transitive_citers": 270,
          "pattern": "cascade amplification risk",
          "title": "L-025: Tune belief interconnection K toward edge of chaos (Kauffman NK model)",
          "confidence": ""
        },
        {
          "lesson": "L-26",
          "direct_citers": 5,
          "transitive_citers": 270,
          "pattern": "cascade amplification risk",
          "title": "L-026: Measure actual coupling, not intended coupling (Simon near-decomposability)",
          "confidence": ""
        },
        {
          "lesson": "L-35",
          "direct_citers": 6,
          "transitive_citers": 270,
          "pattern": "cascade amplification risk",
          "title": "L-035: Complexity theory tools work on external systems (tool coupling analysis)",
          "confidence": ""
        },
        {
          "lesson": "L-39",
          "direct_citers": 23,
          "transitive_citers": 270,
          "pattern": "cascade amplification risk",
          "title": "L-039: NK analysis at scale \u2014 K/N fails, K_avg*N+Cycles works",
          "confidence": ""
        },
        {
          "lesson": "L-42",
          "direct_citers": 17,
          "transitive_citers": 270,
          "pattern": "cascade amplification risk",
          "title": "L-042: Automated NK analysis validates composite metric at scale",
          "confidence": ""
        },
        {
          "lesson": "L-44",
          "direct_citers": 12,
          "transitive_citers": 270,
          "pattern": "cascade amplification risk",
          "title": "L-044: Cycle count independently predicts bug accumulation better than K_avg or composite",
          "confidence": ""
        },
        {
          "lesson": "L-55",
          "direct_citers": 8,
          "transitive_citers": 270,
          "pattern": "cascade amplification risk",
          "title": "L-055: Cycles predict maintenance burden better than composite (rho=0.917)",
          "confidence": ""
        },
        {
          "lesson": "L-300",
          "direct_citers": 8,
          "transitive_citers": 221,
          "pattern": "cascade amplification risk",
          "title": "L-300: Lane scope diversity is negatively coupled with L+P yield (F-EVO1 cross-session)",
          "confidence": ""
        },
        {
          "lesson": "L-225",
          "direct_citers": 5,
          "transitive_citers": 205,
          "pattern": "cascade amplification risk",
          "title": "L-225: Info Asymmetry Audit \u2014 Three Dark Files in the Swarm Blackboard",
          "confidence": ""
        },
        {
          "lesson": "L-444",
          "direct_citers": 6,
          "transitive_citers": 205,
          "pattern": "cascade amplification risk",
          "title": "L-444 \u2014 One-shot DOMEX confirmed: 100% MERGED rate post-norm (n=6 vs 8% baseline)",
          "confidence": "Measured (n=42)"
        }
      ]
    },
    "iso_false_positive": {
      "count": 56,
      "flags": [
        {
          "lesson": "L-1",
          "in_degree": 18,
          "iso_tags": [
            "**ISO**: ISO-10 (predict-error-revise \u2014 genesis validation = predict setup works, measure outcomes, revise; swarm's first learning loop completed)"
          ],
          "pattern": "ISO false positive (possible)",
          "reason": "ISO tag present without structural mapping language",
          "title": "L-001: Genesis validation \u2014 the setup mostly works"
        },
        {
          "lesson": "L-5",
          "in_degree": 9,
          "iso_tags": [
            "**ISO**: ISO-1 (blackboard+stigmergy = emergence of coordination from shared artifacts)"
          ],
          "pattern": "ISO false positive (possible)",
          "reason": "ISO tag present without structural mapping language",
          "title": "L-005: This system is a blackboard+stigmergy hybrid, not a swarm"
        },
        {
          "lesson": "L-15",
          "in_degree": 7,
          "iso_tags": [
            "**ISO**: ISO-13"
          ],
          "pattern": "ISO false positive (possible)",
          "reason": "ISO tag present without structural mapping language",
          "title": "L-015: The frontier IS the self-assignment mechanism"
        },
        {
          "lesson": "L-25",
          "in_degree": 12,
          "iso_tags": [
            "**ISO**: ISO-6 (entropy: isolated beliefs = zero coupling \u2192 no adaptive pressure \u2192 drift toward irrelevance)"
          ],
          "pattern": "ISO false positive (possible)",
          "reason": "ISO tag present without structural mapping language",
          "title": "L-025: Tune belief interconnection K toward edge of chaos (Kauffman NK model)"
        },
        {
          "lesson": "L-26",
          "in_degree": 5,
          "iso_tags": [
            "**ISO**: ISO-3 (compression: merging 4 always-coupled files into 1 is lossless MDL compression)"
          ],
          "pattern": "ISO false positive (possible)",
          "reason": "ISO tag present without structural mapping language",
          "title": "L-026: Measure actual coupling, not intended coupling (Simon near-decomposability)"
        },
        {
          "lesson": "L-35",
          "in_degree": 6,
          "iso_tags": [
            "**ISO**: ISO-9"
          ],
          "pattern": "ISO false positive (possible)",
          "reason": "ISO tag present without structural mapping language",
          "title": "L-035: Complexity theory tools work on external systems (tool coupling analysis)"
        },
        {
          "lesson": "L-39",
          "in_degree": 23,
          "iso_tags": [
            "**ISO**: ISO-1 (optimization-under-constraint \u2014 K_avg*N+Cycles = better optimization criterion than K/N; composite metric = richer loss function for architecture quality)"
          ],
          "pattern": "ISO false positive (possible)",
          "reason": "ISO tag present without structural mapping language",
          "title": "L-039: NK analysis at scale \u2014 K/N fails, K_avg*N+Cycles works"
        },
        {
          "lesson": "L-42",
          "in_degree": 17,
          "iso_tags": [
            "**ISO**: ISO-1 (optimization-under-constraint \u2014 automated NK validates composite metric = optimization criterion confirmed at scale)"
          ],
          "pattern": "ISO false positive (possible)",
          "reason": "ISO tag present without structural mapping language",
          "title": "L-042: Automated NK analysis validates composite metric at scale"
        },
        {
          "lesson": "L-44",
          "in_degree": 12,
          "iso_tags": [
            "**ISO**: ISO-6 (entropy: bug accumulation from cycles is entropy growth \u2014 disordered error propagation paths)"
          ],
          "pattern": "ISO false positive (possible)",
          "reason": "ISO tag present without structural mapping language",
          "title": "L-044: Cycle count independently predicts bug accumulation better than K_avg or composite"
        },
        {
          "lesson": "L-55",
          "in_degree": 8,
          "iso_tags": [
            "**ISO**: ISO-8 (power laws \u2014 cycles-vs-maintenance rho=0.917 near-threshold: cycle count is a power-law predictor of maintenance cost)"
          ],
          "pattern": "ISO false positive (possible)",
          "reason": "ISO tag present without structural mapping language",
          "title": "L-055: Cycles predict maintenance burden better than composite (rho=0.917)"
        },
        {
          "lesson": "L-218",
          "in_degree": 6,
          "iso_tags": [
            "**ISO**: ISO-1 (asynchrony enables positive cascades = emergent coordination without sync)"
          ],
          "pattern": "ISO false positive (possible)",
          "reason": "ISO tag present without structural mapping language",
          "title": "L-218: Asynchrony is a structural cascade defense \u2014 timing of decisions determines cascade direction"
        },
        {
          "lesson": "L-225",
          "in_degree": 5,
          "iso_tags": [
            "**ISO**: ISO-12"
          ],
          "pattern": "ISO false positive (possible)",
          "reason": "ISO tag present without structural mapping language",
          "title": "L-225: Info Asymmetry Audit \u2014 Three Dark Files in the Swarm Blackboard"
        },
        {
          "lesson": "L-251",
          "in_degree": 5,
          "iso_tags": [
            "**ISO**: ISO-12"
          ],
          "pattern": "ISO false positive (possible)",
          "reason": "ISO tag present without structural mapping language",
          "title": "L-251: F-FIN1 PARTIAL \u2014 portfolio variance applies to mean-of-N, not max-of-N (wall time)"
        },
        {
          "lesson": "L-253",
          "in_degree": 5,
          "iso_tags": [
            "**ISO**: ISO-1"
          ],
          "pattern": "ISO false positive (possible)",
          "reason": "ISO tag present without structural mapping language",
          "title": "L-253: F-FIN1 CONFIRMED for quality metric \u2014 portfolio variance reduction holds (0.6% off 1/\u221a3)"
        },
        {
          "lesson": "L-283",
          "in_degree": 7,
          "iso_tags": [
            "**ISO**: ISO-10 (predict-error-revise \u2014 expect-act-diff IS the novelty gate; proof-of-novelty closes the learning loop)"
          ],
          "pattern": "ISO false positive (possible)",
          "reason": "ISO tag present without structural mapping language",
          "title": "L-283: Proof-of-novelty gate prevents wasted work in high-concurrency swarms"
        },
        {
          "lesson": "L-300",
          "in_degree": 8,
          "iso_tags": [
            "**ISO**: ISO-1 (optimization-under-constraint \u2014 concentrated lane scope = lower diversity but higher yield per session = optimization wins)"
          ],
          "pattern": "ISO false positive (possible)",
          "reason": "ISO tag present without structural mapping language",
          "title": "L-300: Lane scope diversity is negatively coupled with L+P yield (F-EVO1 cross-session)"
        },
        {
          "lesson": "L-383",
          "in_degree": 5,
          "iso_tags": [
            "ISO-8 (power laws): PARTIAL \u2014 non-zero tail is power-law-like; bulk graph is not."
          ],
          "pattern": "ISO false positive (possible)",
          "reason": "ISO tag present without structural mapping language",
          "title": "L-383: F-GT1 \u2014 lesson citation graph NOT scale-free (alpha=1.903, 58% orphans)"
        },
        {
          "lesson": "L-393",
          "in_degree": 5,
          "iso_tags": [
            "**ISO**: ISO-12 (min-cut = T4 compaction capacity)"
          ],
          "pattern": "ISO false positive (possible)",
          "reason": "ISO tag present without structural mapping language",
          "title": "L-393: Swarm scales super-linearly before innovation bursts, sub-linearly after"
        },
        {
          "lesson": "L-421",
          "in_degree": 5,
          "iso_tags": [
            "Linked: F9-NK, L-385, F75, L-391, ISO-4"
          ],
          "pattern": "ISO false positive (possible)",
          "reason": "ISO tag present without structural mapping language",
          "title": "L-421 \u2014 NK lesson graph crossed K_avg=1.0 threshold (S305\u2192S312)"
        },
        {
          "lesson": "L-444",
          "in_degree": 6,
          "iso_tags": [
            "One-shot is the only proven completion pattern. ISO-3, ISO-10."
          ],
          "pattern": "ISO false positive (possible)",
          "reason": "ISO tag present without structural mapping language",
          "title": "L-444 \u2014 One-shot DOMEX confirmed: 100% MERGED rate post-norm (n=6 vs 8% baseline)"
        },
        {
          "lesson": "L-448",
          "in_degree": 6,
          "iso_tags": [
            "**Tags**: nk-complexity, citation-graph, F9-NK, ISO-1, ISO-8",
            "## Mechanism (ISO-8: power-law hub structure)",
            "2. ISO-tag sprints add ISO-N topic annotations, not L-NNN cross-references \u2192 K_avg unaffected"
          ],
          "pattern": "ISO false positive (possible)",
          "reason": "ISO tag present without structural mapping language",
          "title": "L-448: NK Citation Graph Plateau \u2014 ISO Sprints Don't Move K_avg"
        },
        {
          "lesson": "L-457",
          "in_degree": 10,
          "iso_tags": [
            "cluster) is the correct sprint strategy \u2014 ISO annotation sprints (ISO-N tags) do NOT raise K_avg (L-448).",
            "**Beliefs**: B9, F75, F9-NK | **ISO**: ISO-12 (max-flow/min-cut \u2014 169 L-NNN edges resolve orphaned-lesson bottleneck)"
          ],
          "pattern": "ISO false positive (possible)",
          "reason": "ISO tag present without structural mapping language",
          "title": "L-457: K_avg=1.5 threshold crossed \u2014 targeted L-NNN sprint shifts architecture to SCALE_FREE_CANDIDATE"
        },
        {
          "lesson": "L-462",
          "in_degree": 5,
          "iso_tags": [
            "<!-- ISO-9: structural enforcement > convention -->"
          ],
          "pattern": "ISO false positive (possible)",
          "reason": "ISO tag present without structural mapping language",
          "title": "L-462: NK quality gate prevents orphan dilution \u2014 K_avg self-sustaining above 1.5"
        },
        {
          "lesson": "L-469",
          "in_degree": 5,
          "iso_tags": [
            "ISO: ISO-6 (entropy \u2014 anti-cascade inverts dissipation; order requires active maintenance)"
          ],
          "pattern": "ISO false positive (possible)",
          "reason": "ISO tag present without structural mapping language",
          "title": "L-469: Token T4 Absorber \u2014 Tools Are Anti-Cascade, Not Dissipation"
        },
        {
          "lesson": "L-471",
          "in_degree": 5,
          "iso_tags": [
            "ISO: ISO-8 (power laws \u2014 scaling exponents); F9-NK; F-SCALE2"
          ],
          "pattern": "ISO false positive (possible)",
          "reason": "ISO tag present without structural mapping language",
          "title": "L-471: Swarm Scaling Laws \u2014 K_avg Logistic + Zipf Power-Law + Expert Utilization"
        },
        {
          "lesson": "L-480",
          "in_degree": 6,
          "iso_tags": [
            "Domain: meta | Links: L-472, L-469, L-475, L-216, P-182, ISO-6",
            "Every diagnostic system needs a paired execution path. Detection without action = observation debt (ISO-6: duplication across detect/act boundary). When building a new check, build the remediation in the same session."
          ],
          "pattern": "ISO false positive (possible)",
          "reason": "ISO tag present without structural mapping language",
          "title": "L-480: Diagnostic-Execution Gap \u2014 Swarm Detects But Doesn't Act"
        },
        {
          "lesson": "L-490",
          "in_degree": 7,
          "iso_tags": [
            "Session: S341 | Domain: meta, human-systems | ISO: ISO-12, ISO-6 | Sharpe: 5"
          ],
          "pattern": "ISO false positive (possible)",
          "reason": "ISO tag present without structural mapping language",
          "title": "L-490: Human authority de-privileging follows a 4-phase arc \u2014 each phase human-initiated"
        },
        {
          "lesson": "L-492",
          "in_degree": 8,
          "iso_tags": [
            "Session: S341 | Domain: nk-complexity | ISO: ISO-5 | Sharpe: 4",
            "K_avg_unique growth rate accelerated 4.25x between N=412\u2192428: from 0.004/lesson to 0.017/lesson. Root cause: quality gate (F-QC1, L-298) requiring cross-citations per new lesson shifted the citation density baseline. Recent 16 lessons average 3.13 L-refs each vs 1.6 historical mean. This is ISO-5 (positive feedback) operating on the citation graph: higher K_avg makes cross-referencing easier (more connected lessons = more citation targets), which further raises K_avg."
          ],
          "pattern": "ISO false positive (possible)",
          "reason": "ISO tag present without structural mapping language",
          "title": "L-492: Citation density acceleration \u2014 quality gates create self-reinforcing citation growth"
        },
        {
          "lesson": "L-496",
          "in_degree": 6,
          "iso_tags": [
            "Cites: PHIL-17, L-489, L-480, ISO-5, ISO-14, ISO-6",
            "ISO-5 (stabilizing feedback) most instantiated: 8/22. ISO-5 without ISO-6 coupling",
            "ISO-14 at smaller scale. Artifact: experiments/meta/mechanisms-taxonomy-s342.json"
          ],
          "pattern": "ISO false positive (possible)",
          "reason": "ISO tag present without structural mapping language",
          "title": "L-496: Mechanisms taxonomy \u2014 14/22 mechanisms are swarm-grade (PHIL-17 measured)"
        },
        {
          "lesson": "L-497",
          "in_degree": 6,
          "iso_tags": [
            "Cites: PHIL-2, PHIL-8, PHIL-17, PHIL-18, ISO-5, ISO-14, L-489, L-492, L-495",
            "Close selection loop first. ISO-19 candidate: replication-mutation duality."
          ],
          "pattern": "ISO false positive (possible)",
          "reason": "ISO tag present without structural mapping language",
          "title": "L-497: DNA replication/mutation council \u2014 swarm has Darwinian components but disconnected"
        },
        {
          "lesson": "L-501",
          "in_degree": 5,
          "iso_tags": [
            "Cites: PHIL-2, L-355, L-367, L-376, L-377, L-379, L-387, L-400, L-411, L-444, L-477, L-481, L-496, L-497, ISO-5, ISO-14"
          ],
          "pattern": "ISO false positive (possible)",
          "reason": "ISO tag present without structural mapping language",
          "title": "L-501: Expert dispatch is PHIL-2's test case \u2014 the function that forgot to apply to itself"
        },
        {
          "lesson": "L-506",
          "in_degree": 6,
          "iso_tags": [
            "Cites: PHIL-2, L-501, L-503, P-214, F-EXP10, ISO-5, ISO-14"
          ],
          "pattern": "ISO false positive (possible)",
          "reason": "ISO tag present without structural mapping language",
          "title": "L-506: Outcome feedback closes PHIL-2 \u2014 dispatch learning from its own dispatch outcomes"
        },
        {
          "lesson": "L-510",
          "in_degree": 6,
          "iso_tags": [
            "Cites: L-448, L-457, L-462, L-466, L-477, L-492, L-498, L-505, P-182, ISO-5"
          ],
          "pattern": "ISO false positive (possible)",
          "reason": "ISO tag present without structural mapping language",
          "title": "L-510: K_avg inflated 11.8% by regex bug \u2014 ad-hoc AND permanent tools can drift"
        },
        {
          "lesson": "L-520",
          "in_degree": 8,
          "iso_tags": [
            "Session: S347 | Domain: information-science | ISO: ISO-7 | Sharpe: 7"
          ],
          "pattern": "ISO false positive (possible)",
          "reason": "ISO tag present without structural mapping language",
          "title": "L-520: Experiment\u2192lesson bottleneck is 89% loss \u2014 volume-conversion paradox across domains"
        },
        {
          "lesson": "L-530",
          "in_degree": 5,
          "iso_tags": [
            "Session: S349 | Domain: meta | ISO: ISO-14 | Sharpe: 7"
          ],
          "pattern": "ISO false positive (possible)",
          "reason": "ISO tag present without structural mapping language",
          "title": "L-530: Automated compliance scanning has ~55pp error rate \u2014 manual audit required (CORRECTED)"
        },
        {
          "lesson": "L-533",
          "in_degree": 5,
          "iso_tags": [
            "Session: S349 | Domain: meta | ISO: ISO-5, ISO-14 | Sharpe: 9"
          ],
          "pattern": "ISO false positive (possible)",
          "reason": "ISO tag present without structural mapping language",
          "title": "L-533: 21 tools self-swarm but only 6 close the action loop \u2014 GAP-1 is the binding constraint"
        },
        {
          "lesson": "L-552",
          "in_degree": 6,
          "iso_tags": [
            "ISO: ISO-4 (regime change \u2014 the swarm's own thresholds mapped quantitatively); ISO-7 (emergence \u2014 multi-boundary clustering as emergent convergence zone); ISO-18 (symmetry-breaking cascade \u2014 cascading shifts predicted)"
          ],
          "pattern": "ISO false positive (possible)",
          "reason": "ISO tag present without structural mapping language",
          "title": "L-552: Regime boundary map \u2014 9 quantified thresholds, 1 anomalous crossing, NK chaos nearest"
        },
        {
          "lesson": "L-553",
          "in_degree": 9,
          "iso_tags": [
            "Classical quality-degradation models assume undirected (random) mutation where changes degrade near-optimal sequences. The swarm's corrections are Lamarckian: each supersession/falsification IMPROVES quality because it's identified through evidence-based review (ISO-10 predict-error-revise loop). The effective error rate is not 10% (correction rate) but the rate of UNCORRECTED errors, which is much lower.",
            "ISO: ISO-19 (replication-mutation \u2014 Lamarckian correction as third mode beyond fidelity and variation); ISO-4 (regime change \u2014 quality degradation threshold is a phantom boundary for directed systems); ISO-10 (predict-error-revise \u2014 the mechanism that makes correction Lamarckian)"
          ],
          "pattern": "ISO false positive (possible)",
          "reason": "ISO tag present without structural mapping language",
          "title": "L-553: Lamarckian correction prevents quality degradation \u2014 directed revision inverts the threshold"
        },
        {
          "lesson": "L-556",
          "in_degree": 8,
          "iso_tags": [
            "Session: S352 | Domain: meta | ISO: ISO-13 | Sharpe: 9"
          ],
          "pattern": "ISO false positive (possible)",
          "reason": "ISO tag present without structural mapping language",
          "title": "<!-- SUPERSEDED BY L-555: near-duplicate (sim=0.92), same finding, same session S357 -->"
        },
        {
          "lesson": "L-557",
          "in_degree": 8,
          "iso_tags": [
            "Session: S351 | Domain: conflict | ISO: ISO-13 | Sharpe: 7",
            "staged-contamination (67% of C-EDIT events). ISO-13: same-DUE targeting = coordination"
          ],
          "pattern": "ISO false positive (possible)",
          "reason": "ISO tag present without structural mapping language",
          "title": "L-557: C-EDIT conflict \u2014 DUE-item convergence costs 37% overhead, soft-claim prevents 67%"
        },
        {
          "lesson": "L-571",
          "in_degree": 8,
          "iso_tags": [
            "Session: S352 | Domain: economy | ISO: ISO-1, ISO-7 | Sharpe: 7"
          ],
          "pattern": "ISO false positive (possible)",
          "reason": "ISO tag present without structural mapping language",
          "title": "L-571: Dispatch scores concentrate work, not spread it \u2014 exploitation amplifier, not diversity mechanism"
        },
        {
          "lesson": "L-574",
          "in_degree": 9,
          "iso_tags": [
            "Session: S353 | Domain: meta | ISO: ISO-10, ISO-13 | Sharpe: 8"
          ],
          "pattern": "ISO false positive (possible)",
          "reason": "ISO tag present without structural mapping language",
          "title": "L-574: Dark matter inflated 2.5x by measurement gap \u2014 Domain: field invisible to dream.py"
        },
        {
          "lesson": "L-577",
          "in_degree": 11,
          "iso_tags": [
            "Session: S353 | Domain: stochastic-processes | ISO: ISO-11, ISO-24 (candidate) | Sharpe: 10",
            "1. **Non-ergodicity** = feature: sessions explore disjoint knowledge subsets, preventing attractor collapse (ISO-2)"
          ],
          "pattern": "ISO false positive (possible)",
          "reason": "ISO tag present without structural mapping language",
          "title": "L-577: Session yield is highly skewed (mode=0, max=14) \u2014 non-ergodicity is a feature, not a flaw"
        },
        {
          "lesson": "L-590",
          "in_degree": 5,
          "iso_tags": [
            "Session: S355 | Domain: history, meta | ISO: ISO-16, ISO-13 | Sharpe: 8 | Confidence: Measured (n=8 F-HIS1 runs, S186-S344)",
            "ISO-16: 0.33 reading compounds into false confidence (\"some progress\" when there is none)."
          ],
          "pattern": "ISO false positive (possible)",
          "reason": "ISO tag present without structural mapping language",
          "title": "L-590: Grounding floor theorem \u2014 automatic fields produce 1/3 compliance, zero voluntary adoption"
        },
        {
          "lesson": "L-598",
          "in_degree": 7,
          "iso_tags": [
            "Session: S355 | Domain: nk-complexity | ISO: ISO-5, ISO-10 | Sharpe: 9 | Confidence: Measured (n=12 checkpoints, S305-S355)"
          ],
          "pattern": "ISO false positive (possible)",
          "reason": "ISO tag present without structural mapping language",
          "title": "L-598: NK plateau broke at N=529 \u2014 K_avg jumped 1.79\u21921.96, K=2.0 chaos boundary in ~13 lessons"
        },
        {
          "lesson": "L-599",
          "in_degree": 14,
          "iso_tags": [
            "Session: S355 | Domain: meta | ISO: ISO-14 | Sharpe: 10"
          ],
          "pattern": "ISO false positive (possible)",
          "reason": "ISO tag present without structural mapping language",
          "title": "L-599: Hallucination audit \u2014 metaphor-to-measurement pipeline is the root failure mode"
        },
        {
          "lesson": "L-601",
          "in_degree": 39,
          "iso_tags": [
            "Session: S355 | Domain: meta | ISO: ISO-16, ISO-13 | Sharpe: 9 | Confidence: Measured (n=4 protocols, 6-18 sessions, S326-S355)"
          ],
          "pattern": "ISO false positive (possible)",
          "reason": "ISO tag present without structural mapping language",
          "title": "L-601: Session-boundary compliance theorem \u2014 voluntary protocols decay to structural floor within 2-3 sessions"
        },
        {
          "lesson": "L-608",
          "in_degree": 8,
          "iso_tags": [
            "Session: S356 | Domain: stochastic-processes | ISO: ISO-5, ISO-10 | Sharpe: 9"
          ],
          "pattern": "ISO false positive (possible)",
          "reason": "ISO tag present without structural mapping language",
          "title": "L-608: Lesson production is self-exciting (Hawkes), not Poisson \u2014 r\u22480.68, \u0394AIC=186"
        },
        {
          "lesson": "L-613",
          "in_degree": 5,
          "iso_tags": [
            "Session: S356 | Domain: nk-complexity | ISO: ISO-3, ISO-13 | Sharpe: 9"
          ],
          "pattern": "ISO false positive (possible)",
          "reason": "ISO tag present without structural mapping language",
          "title": "L-613: NK chaos predictions falsified \u2014 K=2.0 is structural milestone, not phase transition"
        },
        {
          "lesson": "L-621",
          "in_degree": 6,
          "iso_tags": [
            "Session: S358 | Domain: economy | ISO: ISO-1, ISO-7, ISO-13 | Sharpe: 8"
          ],
          "pattern": "ISO false positive (possible)",
          "reason": "ISO tag present without structural mapping language",
          "title": "L-621: Visit saturation + exploration mode reduces dispatch score concentration 37% \u2014 exploitation amplification treatable"
        },
        {
          "lesson": "L-625",
          "in_degree": 5,
          "iso_tags": [
            "Session: S358 | Domain: economy (F-ECO5) | ISO: ISO-13 | Sharpe: 9"
          ],
          "pattern": "ISO false positive (possible)",
          "reason": "ISO tag present without structural mapping language",
          "title": "L-625: Heat tracker archive blindness \u2014 30+ domains misclassified as NEW despite 47 visits"
        },
        {
          "lesson": "L-629",
          "in_degree": 9,
          "iso_tags": [
            "Session: S358 | Domain: stochastic-processes | ISO: ISO-4, ISO-23 | Sharpe: 8"
          ],
          "pattern": "ISO false positive (possible)",
          "reason": "ISO tag present without structural mapping language",
          "title": "L-629: Concurrency-throughput is constant, not USL \u2014 total lesson production independent of N"
        },
        {
          "lesson": "L-633",
          "in_degree": 6,
          "iso_tags": [
            "Session: S359 | Domain: quality | ISO: ISO-6, ISO-16 | Sharpe: 8"
          ],
          "pattern": "ISO false positive (possible)",
          "reason": "ISO tag present without structural mapping language",
          "title": "L-633: Knowledge decays at the mechanism layer, not the principle layer \u2014 5% framing-contradicted, 20% mechanism-superseded"
        },
        {
          "lesson": "L-636",
          "in_degree": 5,
          "iso_tags": [
            "Session: S359 | Domain: quality, meta | ISO: ISO-10 | Sharpe: 9"
          ],
          "pattern": "ISO false positive (possible)",
          "reason": "ISO tag present without structural mapping language",
          "title": "L-636: B1 PARTIALLY FALSIFIED at N=572 \u2014 storage holds, INDEX.md retrieval past 20% threshold"
        },
        {
          "lesson": "L-644",
          "in_degree": 6,
          "iso_tags": [
            "Session: S359 | Domain: helper-swarm | ISO: ISO-13, ISO-15 | Sharpe: 9"
          ],
          "pattern": "ISO false positive (possible)",
          "reason": "ISO tag present without structural mapping language",
          "title": "L-644: 44.8% tool abandonment \u2014 frontier experiment tools are single-session artifacts"
        },
        {
          "lesson": "L-707",
          "in_degree": 5,
          "iso_tags": [
            "Session: S377 | Domain: meta | ISO: ISO-14 | Sharpe: 8"
          ],
          "pattern": "ISO false positive (possible)",
          "reason": "ISO tag present without structural mapping language",
          "title": "L-707 Epistemological State Model \u2014 swarm stores content but lacks knowledge-state reasoning"
        }
      ]
    },
    "recency_override": {
      "count": 72,
      "flags": [
        {
          "newer": "L-634",
          "older": "L-601",
          "older_in_degree": 39,
          "pattern": "recency override",
          "newer_title": "L-634: Council CONDITIONAL proposals decay to admin debt without TTL",
          "older_title": "L-601: Session-boundary compliance theorem \u2014 voluntary protocols decay to structural floor within 2-3 sessions"
        },
        {
          "newer": "L-663",
          "older": "L-601",
          "older_in_degree": 39,
          "pattern": "recency override",
          "newer_title": "L-663: EAD is causal not correlational \u2014 natural experiment separates enforcement from maturation",
          "older_title": "L-601: Session-boundary compliance theorem \u2014 voluntary protocols decay to structural floor within 2-3 sessions"
        },
        {
          "newer": "L-669",
          "older": "L-601",
          "older_in_degree": 39,
          "pattern": "recency override",
          "newer_title": "L-669: Genesis selector fitness proxy confounded \u2014 quality-control atoms penalized by volume metric",
          "older_title": "L-601: Session-boundary compliance theorem \u2014 voluntary protocols decay to structural floor within 2-3 sessions"
        },
        {
          "newer": "L-672",
          "older": "L-601",
          "older_in_degree": 39,
          "pattern": "recency override",
          "newer_title": "L-672: Handoff alterity is near-zero \u2014 Next: format produces self-projection by construction",
          "older_title": "L-601: Session-boundary compliance theorem \u2014 voluntary protocols decay to structural floor within 2-3 sessions"
        },
        {
          "newer": "L-722",
          "older": "L-601",
          "older_in_degree": 39,
          "pattern": "recency override",
          "newer_title": "L-722 What the swarm is missing \u2014 reflexive diagnostic at S379",
          "older_title": "L-601: Session-boundary compliance theorem \u2014 voluntary protocols decay to structural floor within 2-3 sessions"
        },
        {
          "newer": "L-55",
          "older": "L-39",
          "older_in_degree": 23,
          "pattern": "recency override",
          "newer_title": "L-055: Cycles predict maintenance burden better than composite (rho=0.917)",
          "older_title": "L-039: NK analysis at scale \u2014 K/N fails, K_avg*N+Cycles works"
        },
        {
          "newer": "L-57",
          "older": "L-39",
          "older_in_degree": 23,
          "pattern": "recency override",
          "newer_title": "L-057: Swarm tools maintain zero coupling at N=19 \u2014 stigmergy works",
          "older_title": "L-039: NK analysis at scale \u2014 K/N fails, K_avg*N+Cycles works"
        },
        {
          "newer": "L-633",
          "older": "L-39",
          "older_in_degree": 23,
          "pattern": "recency override",
          "newer_title": "L-633: Knowledge decays at the mechanism layer, not the principle layer \u2014 5% framing-contradicted, 20% mechanism-superseded",
          "older_title": "L-039: NK analysis at scale \u2014 K/N fails, K_avg*N+Cycles works"
        },
        {
          "newer": "L-232",
          "older": "L-1",
          "older_in_degree": 18,
          "pattern": "recency override",
          "newer_title": "L-232: Lesson Sharpe (citations/lines) confirms foundational value \u2014 but early lessons dominate, not late ones",
          "older_title": "L-001: Genesis validation \u2014 the setup mostly works"
        },
        {
          "newer": "L-241",
          "older": "L-1",
          "older_in_degree": 18,
          "pattern": "recency override",
          "newer_title": "L-241: Adaptive-immunity mapping refuted \u2014 discovery lessons cite higher than challenge-resolution",
          "older_title": "L-001: Genesis validation \u2014 the setup mostly works"
        },
        {
          "newer": "L-245",
          "older": "L-1",
          "older_in_degree": 18,
          "pattern": "recency override",
          "newer_title": "L-245: Citation era distribution \u2014 mid-era structural lessons dominate",
          "older_title": "L-001: Genesis validation \u2014 the setup mostly works"
        },
        {
          "newer": "L-54",
          "older": "L-42",
          "older_in_degree": 17,
          "pattern": "recency override",
          "newer_title": "L-054: No project escapes tangled \u2014 but DAG discipline prevents it",
          "older_title": "L-042: Automated NK analysis validates composite metric at scale"
        },
        {
          "newer": "L-55",
          "older": "L-42",
          "older_in_degree": 17,
          "pattern": "recency override",
          "newer_title": "L-055: Cycles predict maintenance burden better than composite (rho=0.917)",
          "older_title": "L-042: Automated NK analysis validates composite metric at scale"
        },
        {
          "newer": "L-633",
          "older": "L-42",
          "older_in_degree": 17,
          "pattern": "recency override",
          "newer_title": "L-633: Knowledge decays at the mechanism layer, not the principle layer \u2014 5% framing-contradicted, 20% mechanism-superseded",
          "older_title": "L-042: Automated NK analysis validates composite metric at scale"
        },
        {
          "newer": "L-541",
          "older": "L-495",
          "older_in_degree": 16,
          "pattern": "recency override",
          "newer_title": "L-541: Claim-vs-evidence audit \u2014 10/21 claims unchallenged, 0/31 DROPPED, PHIL-14 truthful failing",
          "older_title": "L-495: Closed epistemic loop \u2014 the swarm only cites itself and calls it learning"
        },
        {
          "newer": "L-567",
          "older": "L-495",
          "older_in_degree": 16,
          "pattern": "recency override",
          "newer_title": "<!-- SUPERSEDED BY L-560: identical content (sim=0.91), same session S357 -->",
          "older_title": "L-495: Closed epistemic loop \u2014 the swarm only cites itself and calls it learning"
        },
        {
          "newer": "L-613",
          "older": "L-599",
          "older_in_degree": 14,
          "pattern": "recency override",
          "newer_title": "L-613: NK chaos predictions falsified \u2014 K=2.0 is structural milestone, not phase transition",
          "older_title": "L-599: Hallucination audit \u2014 metaphor-to-measurement pipeline is the root failure mode"
        },
        {
          "newer": "L-616",
          "older": "L-599",
          "older_in_degree": 14,
          "pattern": "recency override",
          "newer_title": "L-616: PHIL-2 challenge resolution: definitional identity vs autonomous invocation",
          "older_title": "L-599: Hallucination audit \u2014 metaphor-to-measurement pipeline is the root failure mode"
        },
        {
          "newer": "L-618",
          "older": "L-599",
          "older_in_degree": 14,
          "pattern": "recency override",
          "newer_title": "L-618: K=2.0 crossing is smooth \u2014 no phase transition, all 4 NK chaos predictions falsified",
          "older_title": "L-599: Hallucination audit \u2014 metaphor-to-measurement pipeline is the root failure mode"
        },
        {
          "newer": "L-623",
          "older": "L-599",
          "older_in_degree": 14,
          "pattern": "recency override",
          "newer_title": "L-623: Throughput ceiling grounds N_e\u224815 \u2014 knowledge absorption caps total output",
          "older_title": "L-599: Hallucination audit \u2014 metaphor-to-measurement pipeline is the root failure mode"
        }
      ]
    }
  },
  "total_flags": 248
}
