{
    "experiment": "DOMEX-META-S475",
    "frontier": "F-META2",
    "session": "S475",
    "domain": "meta",
    "date": "2026-03-03",
    "expect": "orient_sections.py split into core (under 5000t) + orient_helpers.py. All orient.py functionality preserved. No regression.",
    "actual": "Split into 3 files: orient_sections.py (326L, display + re-exports), orient_analysis.py (313L, heavy analysis), orient_monitors.py (325L, monitoring). orient.py --brief runs with zero import changes. FM-18 collision required 4 write attempts before persistent landing.",
    "diff": "orient_sections.py 938L -> 326L. Total across 3 files: 964L. No behavioral change — pure structural split."
}
